powershellmagic.py
powershellmagic-0.1.0.dist-info/DESCRIPTION.rst
powershellmagic-0.1.0.dist-info/METADATA
powershellmagic-0.1.0.dist-info/metadata.json
powershellmagic-0.1.0.dist-info/RECORD
powershellmagic-0.1.0.dist-info/top_level.txt
powershellmagic-0.1.0.dist-info/WHEEL
