Metadata-Version: 2.0
Name: powershellmagic
Version: 0.1.0
Summary: IPython magic for Windows PowerShell
Home-page: https://github.com/etgalloway/powershellmagic
Author: Eric Galloway
Author-email: ericgalloway@gmail.com
License: UNKNOWN
Platform: UNKNOWN
Classifier: Environment :: Win32 (MS Windows)
Classifier: Framework :: IPython
Classifier: License :: OSI Approved :: BSD License
Classifier: Programming Language :: Python
Classifier: Programming Language :: Python :: 2
Classifier: Programming Language :: Python :: 3
Classifier: Topic :: System :: Shells
Requires-Dist: ipython
